gifconvrt_seokwoolee/__init__.py
gifconvrt_seokwoolee/gif_converter.py
gifconvrt_seokwoolee-1.0.2.dist-info/LICENSE
gifconvrt_seokwoolee-1.0.2.dist-info/METADATA
gifconvrt_seokwoolee-1.0.2.dist-info/WHEEL
gifconvrt_seokwoolee-1.0.2.dist-info/top_level.txt
gifconvrt_seokwoolee-1.0.2.dist-info/RECORD
